carabao/__init__.py
carabao/__main__.py
carabao/constants.py
carabao/core.py
carabao/form.py
carabao/settings.py
carabao/cfg/base_cfg.py
carabao/cfg/public_cfg.py
carabao/cfg/secret_cfg.py
carabao/cli/__init__.py
carabao/cli/init_prompter.py
carabao/cli/sample.carabao.cfg
carabao/cli/sample.settings.py
carabao/cli/cmd_dev/__init__.py
carabao/cli/cmd_dev/display.py
carabao/cli/cmd_dev/display.tcss
carabao/cli/cmd_new/__init__.py
carabao/cli/cmd_new/display.py
carabao/cli/cmd_new/display.tcss
carabao/cli/cmd_new/item.py
carabao/cli/sample/basic.py
carabao/cli/sample/batched_subscriber.py
carabao/cli/sample/branching.py
carabao/cli/sample/factory.py
carabao/cli/sample/form.py
carabao/cli/sample/passive.py
carabao/cli/sample/subscriber.py
carabao/errors/__init__.py
carabao/errors/environment.py
carabao/helpers/prompter.py
carabao/helpers/stdout_catcher.py
carabao/helpers/utils.py
carabao/lanes/__init__.py
carabao/lanes/log_to_db.py
carabao/lanes/network_health.py
carabao/lanes/pretty_env.py
carabao-1.20.2.dist-info/licenses/LICENSE
carabao-1.20.2.dist-info/METADATA
carabao-1.20.2.dist-info/WHEEL
carabao-1.20.2.dist-info/entry_points.txt
carabao-1.20.2.dist-info/top_level.txt
carabao-1.20.2.dist-info/RECORD
