Metadata-Version: 2.4
Name: carabao
Version: 1.20.2
Summary: Moooove your data with ease using our udderly simple pipeline framework.
Author: Talisik Team
Platform: unix
Platform: linux
Platform: osx
Platform: cygwin
Platform: win32
Classifier: Programming Language :: Python :: 3
Classifier: Programming Language :: Python :: 3 :: Only
Classifier: Programming Language :: Python :: 3.8
Classifier: Programming Language :: Python :: 3.9
Classifier: Programming Language :: Python :: 3.10
Classifier: Programming Language :: Python :: 3.11
Classifier: Programming Language :: Python :: 3.12
Requires-Python: >=3.6
License-File: LICENSE
Requires-Dist: async-timeout
Requires-Dist: dnspython
Requires-Dist: fun-things
Requires-Dist: lazy-main==0.6.*
Requires-Dist: python-dotenv
Requires-Dist: simple-chalk
Requires-Dist: typing-extensions
Requires-Dist: typer
Requires-Dist: lane2lane==1.11.*
Requires-Dist: textual
Requires-Dist: textual-slider
Dynamic: license-file
